symbolica-1.2.0.dist-info/METADATA
symbolica-1.2.0.dist-info/WHEEL
symbolica-1.2.0.dist-info/licenses/LICENSE
symbolica/__init__.py
symbolica/community/__init__.py
symbolica/community/example_extension/__init__.py
symbolica/community/example_extension/__init__.pyi
symbolica/community/idenso/__init__.py
symbolica/community/idenso/__init__.pyi
symbolica/community/spenso/__init__.py
symbolica/community/spenso/__init__.pyi
symbolica/community/vakint/__init__.py
symbolica/community/vakint/__init__.pyi
symbolica/core.abi3.so
symbolica/core.pyi
symbolica/py.typed
symbolica-1.2.0.dist-info/RECORD
