Metadata-Version: 2.4
Name: symbolica
Version: 1.2.0
Classifier: Development Status :: 5 - Production/Stable
Classifier: Programming Language :: Rust
Classifier: Topic :: Scientific/Engineering :: Mathematics
License-File: LICENSE
Summary: Community-enhanced version of Symbolica: a blazing fast computer algebra system
Keywords: math,algebra,polynomial,expression,manipulation
Author-email: Ben Ruijl <benruyl@gmail.com>, Lucien Huber <mail@lucien.ch>, Valentin Hirschi <valentin.hirschi@gmail.com>
Requires-Python: >=3.7
Project-URL: homepage, https://symbolica.io
Project-URL: repository, https://github.com/symbolica-dev/symbolica
